oarepo_records_draft/__init__.py
oarepo_records_draft/_i18n.py
oarepo_records_draft/cli.py
oarepo_records_draft/config.py
oarepo_records_draft/endpoints.py
oarepo_records_draft/exceptions.py
oarepo_records_draft/ext.py
oarepo_records_draft/links.py
oarepo_records_draft/mappings.py
oarepo_records_draft/merge.py
oarepo_records_draft/proxies.py
oarepo_records_draft/record.py
oarepo_records_draft/rest.py
oarepo_records_draft/signals.py
oarepo_records_draft/types.py
oarepo_records_draft/version.py
oarepo_records_draft/views.py
oarepo_records_draft/actions/__init__.py
oarepo_records_draft/actions/edit.py
oarepo_records_draft/actions/files.py
oarepo_records_draft/actions/publish.py
oarepo_records_draft/actions/unpublish.py
oarepo_records_draft/translations/messages.pot
oarepo_records_draft/translations/cs/LC_MESSAGES/messages.mo
oarepo_records_draft/translations/cs/LC_MESSAGES/messages.po
oarepo_records_draft/translations/en/LC_MESSAGES/messages.mo
oarepo_records_draft/translations/en/LC_MESSAGES/messages.po
oarepo_records_draft-5.5.8.dist-info/LICENSE
oarepo_records_draft-5.5.8.dist-info/METADATA
oarepo_records_draft-5.5.8.dist-info/WHEEL
oarepo_records_draft-5.5.8.dist-info/entry_points.txt
oarepo_records_draft-5.5.8.dist-info/top_level.txt
oarepo_records_draft-5.5.8.dist-info/RECORD
