Metadata-Version: 2.1
Name: oarepo-records-draft
Version: 5.5.8
Summary: Handling Draft and Production invenio records in one package
Home-page: https://github.com/oarepo/oarepo-records-draft
Author: Mirek Šimek
Author-email: miroslav.simek@vscht.cz
License: MIT
Platform: any
Classifier: Environment :: Web Environment
Classifier: Intended Audience :: Developers
Classifier: License :: OSI Approved :: MIT License
Classifier: Operating System :: OS Independent
Classifier: Programming Language :: Python
Classifier: Topic :: Internet :: WWW/HTTP :: Dynamic Content
Classifier: Topic :: Software Development :: Libraries :: Python Modules
Classifier: Programming Language :: Python :: 3
Classifier: Programming Language :: Python :: 3.8
Classifier: Development Status :: 4 - Beta
License-File: LICENSE
Requires-Dist: wrapt (>=1.11.2)
Requires-Dist: oarepo-validate
Requires-Dist: deepmerge
Requires-Dist: NamedAtomicLock
Provides-Extra: dev
Requires-Dist: oarepo[tests] (~=3.3.0) ; extra == 'dev'
Requires-Dist: Babel ; extra == 'dev'
Provides-Extra: tests
Requires-Dist: oarepo[tests] (~=3.3.0) ; extra == 'tests'
Provides-Extra: tests_files
Requires-Dist: invenio-files-rest ; extra == 'tests_files'
